{
    "name": "Global Information",
    "numberOfRequests": {
        "total": 32,
        "ok": 28,
        "ko": 4
    },
    "minResponseTime": {
        "total": 101,
        "ok": 102,
        "ko": 101
    },
    "maxResponseTime": {
        "total": 544,
        "ok": 267,
        "ko": 544
    },
    "meanResponseTime": {
        "total": 181,
        "ok": 176,
        "ko": 214
    },
    "standardDeviation": {
        "total": 83,
        "ok": 49,
        "ko": 191
    },
    "percentiles1": {
        "total": 160,
        "ok": 169,
        "ko": 105
    },
    "percentiles2": {
        "total": 224,
        "ok": 224,
        "ko": 216
    },
    "percentiles3": {
        "total": 255,
        "ok": 246,
        "ko": 478
    },
    "percentiles4": {
        "total": 458,
        "ok": 261,
        "ko": 531
    },
    "group1": {
    "name": "t < 800 ms",
    "count": 28,
    "percentage": 88
},
    "group2": {
    "name": "800 ms < t < 1200 ms",
    "count": 0,
    "percentage": 0
},
    "group3": {
    "name": "t > 1200 ms",
    "count": 0,
    "percentage": 0
},
    "group4": {
    "name": "failed",
    "count": 4,
    "percentage": 13
},
    "meanNumberOfRequestsPerSecond": {
        "total": 0.5714285714285714,
        "ok": 0.5,
        "ko": 0.07142857142857142
    }
}